alectiolite/__init__.py
alectiolite/init.py
alectiolite/backend/__init__.py
alectiolite/backend/backend_server.py
alectiolite/backend/s3_client.py
alectiolite/backend/sql_client.py
alectiolite/backend/torch_utils/__init__.py
alectiolite/backend/torch_utils/boxutils.py
alectiolite/callbacks/__init__.py
alectiolite/callbacks/base.py
alectiolite/callbacks/curate.py
alectiolite/callbacks/filter.py
alectiolite/config/__init__.py
alectiolite/config/default_backend_config.py
alectiolite/curate/__init__.py
alectiolite/curate/classification.py
alectiolite/curate/init.py
alectiolite/curate/object_detection.py
alectiolite/curate/object_segmentation.py
alectiolite/filter/__init__.py
alectiolite/logger/__init__.py
alectiolite/logger/db_logger.py
alectiolite/logger/logger.py
alectiolite/logger/pickle_logger.py
alectiolite/metrics/__init__.py
alectiolite/metrics/classification/__init__.py
alectiolite/metrics/classification/classification.py
alectiolite/metrics/multilabel_classification/__init__.py
alectiolite/metrics/multilabel_classification/multilabel_classification.py
alectiolite/metrics/object_detection/CM.py
alectiolite/metrics/object_detection/__init__.py
alectiolite/metrics/object_detection/_object_detection.py
alectiolite/metrics/object_detection/imports.py
alectiolite/metrics/object_detection/utils.py
alectiolite/metrics/object_segmentation/SegCM.py
alectiolite/metrics/object_segmentation/__init__.py
alectiolite/metrics/object_segmentation/_object_segmentation.py
alectiolite/metrics/object_segmentation/rangeutils.py
alectiolite/proto/__init__.py
alectiolite/proto/bidirectional_pb2.py
alectiolite/proto/bidirectional_pb2_grpc.py
alectiolite-0.0.1.dist-info/LICENSE
alectiolite-0.0.1.dist-info/METADATA
alectiolite-0.0.1.dist-info/WHEEL
alectiolite-0.0.1.dist-info/top_level.txt
alectiolite-0.0.1.dist-info/RECORD
